deeprankcore/__init__.py
deeprankcore/dataset.py
deeprankcore/query.py
deeprankcore/trainer.py
deeprankcore/domain/__init__.py
deeprankcore/domain/aminoacid_summary.xlsx
deeprankcore/domain/aminoacidlist.py
deeprankcore/domain/edgestorage.py
deeprankcore/domain/gridstorage.py
deeprankcore/domain/losstypes.py
deeprankcore/domain/nodestorage.py
deeprankcore/domain/targetstorage.py
deeprankcore/domain/forcefield/__init__.py
deeprankcore/domain/forcefield/patch.top
deeprankcore/domain/forcefield/protein-allhdg5-4_new.param
deeprankcore/domain/forcefield/protein-allhdg5-5_new.top
deeprankcore/domain/forcefield/residue-classes
deeprankcore/features/__init__.py
deeprankcore/features/components.py
deeprankcore/features/conservation.py
deeprankcore/features/contact.py
deeprankcore/features/exposure.py
deeprankcore/features/irc.py
deeprankcore/features/secondary_structure.py
deeprankcore/features/surfacearea.py
deeprankcore/molstruct/__init__.py
deeprankcore/molstruct/aminoacid.py
deeprankcore/molstruct/atom.py
deeprankcore/molstruct/pair.py
deeprankcore/molstruct/residue.py
deeprankcore/molstruct/structure.py
deeprankcore/molstruct/variant.py
deeprankcore/neuralnets/__init__.py
deeprankcore/neuralnets/cnn/__init__.py
deeprankcore/neuralnets/cnn/model3d.py
deeprankcore/neuralnets/gnn/__init__.py
deeprankcore/neuralnets/gnn/alignmentnet.py
deeprankcore/neuralnets/gnn/foutnet.py
deeprankcore/neuralnets/gnn/ginet.py
deeprankcore/neuralnets/gnn/ginet_nocluster.py
deeprankcore/neuralnets/gnn/naive_gnn.py
deeprankcore/neuralnets/gnn/sgat.py
deeprankcore/tools/__init__.py
deeprankcore/tools/classdiagrams.sh
deeprankcore/tools/plotgraph.py
deeprankcore/tools/target.py
deeprankcore/tools/visualization/__init__.py
deeprankcore/tools/visualization/baseimport.py
deeprankcore/tools/visualization/embedding.py
deeprankcore/tools/visualization/h5x_menu.py
deeprankcore/tools/visualization/plotting.py
deeprankcore/utils/__init__.py
deeprankcore/utils/buildgraph.py
deeprankcore-2.0.0.dist-info/LICENSE
deeprankcore-2.0.0.dist-info/METADATA
deeprankcore-2.0.0.dist-info/WHEEL
deeprankcore-2.0.0.dist-info/top_level.txt
deeprankcore-2.0.0.dist-info/RECORD
