Metadata-Version: 2.1
Name: deeprankcore
Version: 2.0.0
Summary: deeprankcore allows to train graph neural networks to classify protein-protein interface with a greater flexibility for the user.
Home-page: https://github.com/DeepRank/deeprank-core
Project-URL: Bug Tracker, https://github.com/DeepRank/deeprank-core/issues
Keywords: graph neural network,protein-protein interface,pytorch
Classifier: Intended Audience :: Developers
Classifier: License :: OSI Approved :: Apache Software License
Classifier: Natural Language :: English
Classifier: Programming Language :: Python :: 3
Classifier: Programming Language :: Python :: 3.9
Classifier: Programming Language :: Python :: 3.10
Requires-Python: >=3.9
License-File: LICENSE
Requires-Dist: tables (>=3.7)
Requires-Dist: numpy (>=1.21.5)
Requires-Dist: scipy (>=1.8.0)
Requires-Dist: h5py (>=3.6.0)
Requires-Dist: h5xplorer
Requires-Dist: networkx (>=2.6.3)
Requires-Dist: matplotlib (>=3.5.1)
Requires-Dist: pdb2sql (>=0.5.1)
Requires-Dist: scikit-learn (>=1.0.2)
Requires-Dist: chart-studio (>=1.1.0)
Requires-Dist: biopython (>=1.81)
Requires-Dist: python-louvain (>=0.16)
Requires-Dist: markov-clustering (>=0.0.6.dev0)
Requires-Dist: tqdm (>=4.63.0)
Requires-Dist: freesasa (==2.1.0)
Requires-Dist: tensorboard (>=2.9.0)
Requires-Dist: protobuf (<=3.20.1)
Provides-Extra: dev
Requires-Dist: yapf ; extra == 'dev'
Requires-Dist: isort ; extra == 'dev'
Provides-Extra: doc
Requires-Dist: recommonmark ; extra == 'doc'
Requires-Dist: sphinx ; extra == 'doc'
Requires-Dist: sphinx-rtd-theme ; extra == 'doc'
Provides-Extra: publishing
Requires-Dist: build ; extra == 'publishing'
Requires-Dist: twine ; extra == 'publishing'
Requires-Dist: wheel ; extra == 'publishing'
Provides-Extra: test
Requires-Dist: pylint (<=2.15.3) ; extra == 'test'
Requires-Dist: prospector[with_pyroma] (<=1.7.7) ; extra == 'test'
Requires-Dist: bump2version ; extra == 'test'
Requires-Dist: coverage ; extra == 'test'
Requires-Dist: pycodestyle ; extra == 'test'
Requires-Dist: pytest ; extra == 'test'
Requires-Dist: pytest-cov ; extra == 'test'
Requires-Dist: pytest-runner ; extra == 'test'
Requires-Dist: coveralls ; extra == 'test'
